README.md
setup.py
src/MicroPyDD.egg-info/PKG-INFO
src/MicroPyDD.egg-info/SOURCES.txt
src/MicroPyDD.egg-info/dependency_links.txt
src/MicroPyDD.egg-info/requires.txt
src/MicroPyDD.egg-info/top_level.txt
src/micropydd/__init__.py
src/micropydd/actions.py
src/micropydd/config.py
src/micropydd/decorators.py
src/micropydd/exceptions.py
src/micropydd/logger.py
src/micropydd/models.py
src/micropydd/module.py
src/micropydd/utils.py