Metadata-Version: 2.1
Name: MicroPyDD
Version: 0.0.7
Summary: MicroPyDD simplyfies managements of microservice boilerplates code
Home-page: UNKNOWN
Author: Danilo Delizia
Author-email: ddelizia@gmail.com
License: UNKNOWN
Platform: UNKNOWN
